{
    "title": "Your Enterprise @ Startup Speed",
    "subtitle": "Create cloud apps, apis & functions without coding",
    "contents": [
        {
            "title": "Apps",
            "image": "http://res.cloudinary.com/dzmrr9uj9/image/upload/webapp.png"
        },
        {
            "title": "API",
            "image": "http://res.cloudinary.com/dzmrr9uj9/image/upload/restapi.png"
        },
        {
            "title": "Functions",
            "image": "http://res.cloudinary.com/dzmrr9uj9/image/upload/function.png"
        }
    ]
}